samsungTVlegacy/__init__.py
samsungTVlegacy/__main__.py
samsungTVlegacy/exceptions.py
samsungTVlegacy/interactive.py
samsungTVlegacy/remote.py
samsungTVlegacy/remote_legacy.py
samsungTVlegacy/remote_websocket.py
samsungTVlegacy-0.1.1.dist-info/LICENSE
samsungTVlegacy-0.1.1.dist-info/METADATA
samsungTVlegacy-0.1.1.dist-info/WHEEL
samsungTVlegacy-0.1.1.dist-info/entry_points.txt
samsungTVlegacy-0.1.1.dist-info/top_level.txt
samsungTVlegacy-0.1.1.dist-info/RECORD
