Metadata-Version: 2.1
Name: samsungTVlegacy
Version: 0.1.1
Summary: Remote control Samsung televisions via TCP/IP connection
Home-page: https://github.com/ClearlyDazed/samsungTVlegacy
Author: originally Lauri Niskanen
Author-email: ape@ape3000.com
License: MIT
Platform: UNKNOWN
Classifier: Development Status :: 4 - Beta
Classifier: Environment :: Console
Classifier: License :: OSI Approved :: MIT License
Classifier: Programming Language :: Python :: 3
Classifier: Topic :: Home Automation
Provides-Extra: interactive_ui
Requires-Dist: curses ; extra == 'interactive_ui'
Provides-Extra: websocket
Requires-Dist: websocket-client ; extra == 'websocket'
